{"div":{"@xmlns":"http://www.tei-c.org/ns/1.0","@type":"article","@xml:id":"MG-1709-03_343","head":{"value":"Enigme","id":"/div/head"},"bibl":{"title":{"value":"Mercure galant","id":"/div/bibl/title"},"#":{"value":", mars 1709 [tome 3], p. 343-345.","id":"/div/bibl/#"}},"p":[{"#1":{"value":"Le mot de l’Enigme du mois dernier, estoit ","id":"/div/p[0]/#1"},"hi":{"@rend":"i","#":{"value":"l’Esprit","id":"/div/p[0]/hi/#"}},"#2":{"value":". Tous ceux qui en ont appris le mot, sans avoir pû le deviner, l’ont trouvé tres-juste, &amp; cependant l’esprit n’a point servi à faire trouver son semblable ; de maniere que le mot de cette Enigme n’a esté trouvé que par tres-peu de personnes. Ce sont Mrs l’Abbé de Saint Didier ; d’Argentré, de Roüen ; de la Claus, Capitaine d’Infanterie ; le plus jeune des Conseillers ; &amp; G.A.C. qui l’a expliquée en Vers. Mlles de la Durandiere ; de la Valterie ; de Penneval, &amp; de Bus ; la plus jeune des belles Dames de la ruë des Bernardins ; la jeune Muse renaissante G.O. &amp; la Solitaire de la ruë aux Féves.","id":"/div/p[0]/#2"}},"Je vous envoye une Enigme nouvelle."],"quote":{"label":{"value":"ENIGME.","id":"/div/quote/label"},"lg":{"l":[{"hi":{"@rend":"i","#":{"value":"Mon corps est delicat autant qu’il le peut estre,","id":"/div/quote/lg/l[0]/hi/#"}}},{"hi":{"@rend":"i","#":{"value":"Je ne crains pourtant pas les injures du temps","id":"/div/quote/lg/l[1]/hi/#"}}},{"hi":{"@rend":"i","#":{"value":"Où la necessité m’expose tous les ans,","id":"/div/quote/lg/l[2]/hi/#"}}},{"hi":{"@rend":"i","#":{"value":"Quand pour le bien public on m’oblige à paroistre ;","id":"/div/quote/lg/l[3]/hi/#"}}},{"hi":{"@rend":"i","#":{"value":"Sans armes ny baston je fais peur aux filoux,","id":"/div/quote/lg/l[4]/hi/#"}}},{"hi":{"@rend":"i","#":{"value":"Ma presence pour eux est un objet contraire,","id":"/div/quote/lg/l[5]/hi/#"}}},{"hi":{"@rend":"i","#":{"value":"Les plus déterminez ne peuvent plus rien faire","id":"/div/quote/lg/l[6]/hi/#"}}},{"hi":{"@rend":"i","#":{"value":"Sans s’exposer souvent à de terribles coups ;","id":"/div/quote/lg/l[7]/hi/#"}}},{"hi":{"@rend":"i","#":{"value":"Quelquefois cependant je leur suis tres-utile,","id":"/div/quote/lg/l[8]/hi/#"}}},{"hi":{"@rend":"i","#":{"value":"Ainsi qu’à tout Mortel, quand il va par la Ville.","id":"/div/quote/lg/l[9]/hi/#"}}}]}}}}