{"div":{"@xmlns":"http://www.tei-c.org/ns/1.0","@type":"article","@xml:id":"MG-1696-04_007","@resp":"wordpro","head":{"value":"Priere pour le Roy","id":"/div/head"},"bibl":{"title":{"value":"Mercure galant","id":"/div/bibl/title"},"#":{"value":", avril 1696 [tome 4], p. 7-10.","id":"/div/bibl/#"}},"p":{"value":"Le zele ardent qu’ont les François pour le Roy continuë toujours, &amp; comme le temps approche où la Campagne doit s’ouvrir, l’amour que les grandes qualitez de cet Auguste Monarque, a fait naistre dans le cœur de tous ses Sujets, les engage à renouveller les vœux qu’ils font tous les ans pour la prosperité de ses armes. Ils y sont d’autant plus portez, que la Religion ayant grande part à la guerre qui agite toute l’Europe depuis tant d’années, c’est soutenir la cause de Dieu que de souhaiter que les desseins de Sa M. réussissent. Un interest si noble &amp; si saint, exprimé heureusement dans le peu de Vers que vous allez lire, nous doit faire esperer beaucoup des Prieres qu’on adresse au Ciel pour en obtenir le secours qui a toujours éclaté visiblement pour la France.","id":"/div/p"},"quote":[{"label":{"value":"PRIERE POUR LE ROY.","id":"/div/quote[0]/label"},"lg":{"l":[{"@rend":"i","#":{"value":"Seigneur, que vostre main benisse","id":"/div/quote[0]/lg/l[0]/#"}},{"@rend":"i","#":{"value":"Loüis, le plus grand des Mortels,","id":"/div/quote[0]/lg/l[1]/#"}},{"@rend":"i","#":{"value":"Et pour l’honneur de vos Autels","id":"/div/quote[0]/lg/l[2]/#"}},{"@rend":"i","#":{"value":"Faites qu’en tout son desir s’accomplisse.","id":"/div/quote[0]/lg/l[3]/#"}}]}},{"label":{"value":"AUTRE.","id":"/div/quote[1]/label"},"lg":{"l":[{"@rend":"i","#":{"value":"Au Char du grand Loüis enchaîne la Victoire,","id":"/div/quote[1]/lg/l[0]/#"}},{"@rend":"i","#":{"value":"Seigneur, s’il ne combat que pour ta sainte Loy,","id":"/div/quote[1]/lg/l[1]/#"}},{"@rend":"i","#":{"value":" Daigne prendre soin de sa gloire,","id":"/div/quote[1]/lg/l[2]/#"}},{"@rend":"i","#":{"value":"Et combattre pour luy lors qu’il combat pour toy.","id":"/div/quote[1]/lg/l[3]/#"}}]}}]}}