{"div":{"@xmlns":"http://www.tei-c.org/ns/1.0","@type":"article","@xml:id":"MG-1700-04_215","@resp":"angele","head":{"value":"Menuet","id":"/div/head"},"bibl":{"title":{"value":"Mercure galant","id":"/div/bibl/title"},"#":{"value":", avril 1700 [tome 4], p. 215-216.","id":"/div/bibl/#"}},"p":{"#":[{"#":{"value":"J'ay à vous parler d'une merveille de vostre Sexe. C'est de Mademoiselle de S Olon, Fille de M","id":"/div/p/#[0]/#"}},{"hi":{"@rend":"sup","#":{"value":"r","id":"/div/p/#[1]/hi/#"}}},{"#":{"value":" de S Olon, qui a esté Ambassadeur vers le Roy de Maroc. Cette jeune Demoiselle, qui n'a que douze ans, joüe tres bien du Clavessin, &amp; sçait la Musique en perfection. Vous en jugerez par le Menuet que je vous envoye, &amp; qui est de sa composition. Un Ami de M","id":"/div/p/#[2]/#"}},{"hi":{"@rend":"sup","#":{"value":"r","id":"/div/p/#[3]/hi/#"}}},{"#":{"value":" son Pere, l'ayant entendu, fit ces paroles pour estre chantées sur ce même Air.","id":"/div/p/#[4]/#"}}]},"quote":{"label":{"value":"MENUET.","id":"/div/quote/label"},"note":{"@resp":"author","@place":"margin","#1":{"value":"[Le] Menuet, ","id":"/div/quote/note/#1"},"hi":{"@rend":"i","#":{"value":"Auprés de vous","id":"/div/quote/note/hi/#"}},"#2":{"value":", page 216.","id":"/div/quote/note/#2"}},"lg":{"l":[{"@rend":"i","#":{"value":"Auprés de vous qui se pourroit défendre","id":"/div/quote/lg/l[0]/#"}},{"@rend":"i","#":{"value":"De soupirer &amp; de former des vœux ?","id":"/div/quote/lg/l[1]/#"}},{"@rend":"i","#":{"value":"Belle Philis, il faut se rendre,","id":"/div/quote/lg/l[2]/#"}},{"@rend":"i","#":{"value":"On est charmé quand on voit vos beaux yeux.","id":"/div/quote/lg/l[3]/#"}}]}},"ref":{"@target":"images/1700-04_215.JPG","figure":{"graphic":{"@url":"images/1700-04_215.JPG"}}}}}