{"div":{"@xmlns":"http://www.tei-c.org/ns/1.0","@type":"article","@xml:id":"MG-1680-02_283","@resp":"mercure","head":{"value":"[Air de Mademoiselle de Saint Jean de Saint Malo]*","id":"/div/head"},"bibl":{"title":{"value":"Mercure galant","id":"/div/bibl/title"},"#":{"value":", février 1680 [tome 3], p. 283-285.","id":"/div/bibl/#"},"note":{"@resp":"editor","@place":"margin","#1":{"value":"D'après le chroniqueur du Mercure cet air est du même auteur que l'air ","id":"/div/bibl/note/#1"},"hi":{"@rend":"i","ref":{"@target":"MG-1680-03a_015","#":{"value":"Comment pourrais-je voir","id":"/div/bibl/note/hi/ref/#"}}},"#2":{"value":", attribué de manière certaine à Bacilly.","id":"/div/bibl/note/#2"}}},"p":{"#1":{"value":"Je me souviens que vous m’avez fort vanté les Paroles de deux Chansons, que vous avez trouvées parmy beaucoup d’autres dans les Journaux de l’illustre Autheur, qui me fait la grace de m’en donner depuis quelque temps pour toutes mes Lettres. Ces Paroles commencent par ","id":"/div/p/#1"},"hi":{"@rend":"i","#":{"value":"Croyez-moy, croyez-moy, mon cœur, &amp;c. Sortez, petits Oyseaux. &amp;c.","id":"/div/p/hi/#"}},"#2":{"value":" J’ay découvert qu’elles sont de Mademoiselle de Saint Jean de Saint Malo, &amp; comme il m’en est tombé entre les mains de nouvelles de sa façon, que le mesme Autheur a mises en Air, je ne doute point que je ne vous fasse plaisir de vous les donner notées. Vous ne pouvez rien apprendre qui soit plus nouveau.","id":"/div/p/#2"}},"quote":{"label":{"value":"AIR.","id":"/div/quote/label"},"note":{"@":{"resp":"author","place":"margin"},"#":[{"hi":{"@rend":"i","#":{"value":"Avis pour placer les Figures","id":"/div/quote/note/#[0]/hi/#"}}},{"#":{"value":" : l’Air qui commence par ","id":"/div/quote/note/#[1]/#"}},{"hi":{"@rend":"i","#":{"value":"Que je crains de Tircis le respect dangereux","id":"/div/quote/note/#[2]/hi/#"}}},{"#":{"value":", doit regarder la page 285.","id":"/div/quote/note/#[3]/#"}}]},"lg":{"l":[{"@rend":"i","#":{"value":"Que je crains de Tircis le respect dangereux !","id":"/div/quote/lg/l[0]/#"}},{"@rend":"i","seg":[{"@type":"tab","#":{"value":"    ","id":"/div/quote/lg/l[1]/seg[0]/#"}},{"@type":"tab","#":{"value":"    ","id":"/div/quote/lg/l[1]/seg[1]/#"}}],"#":{"value":"Et que ses regards amoureux","id":"/div/quote/lg/l[1]/#"}},{"@rend":"i","seg":{"@type":"tab","#":{"value":"    ","id":"/div/quote/lg/l[2]/seg/#"}},"#":{"value":"Avec son cœur toûjours d’intelligence,","id":"/div/quote/lg/l[2]/#"}},{"@rend":"i","seg":[{"@type":"tab","#":{"value":"    ","id":"/div/quote/lg/l[3]/seg[0]/#"}},{"@type":"tab","#":{"value":"    ","id":"/div/quote/lg/l[3]/seg[1]/#"}}],"#":{"value":"Me font redouter son silence !","id":"/div/quote/lg/l[3]/#"}},{"@rend":"i","seg":[{"@type":"tab","#":{"value":"    ","id":"/div/quote/lg/l[4]/seg[0]/#"}},{"@type":"tab","#":{"value":"    ","id":"/div/quote/lg/l[4]/seg[1]/#"}}],"#":{"value":"Par ce langage ingénieux,","id":"/div/quote/lg/l[4]/#"}},{"@rend":"i","#":{"value":"Amour cause à mon cœur de secretes alarmes ;","id":"/div/quote/lg/l[5]/#"}},{"@rend":"i","seg":[{"@type":"tab","#":{"value":"    ","id":"/div/quote/lg/l[6]/seg[0]/#"}},{"@type":"tab","#":{"value":"    ","id":"/div/quote/lg/l[6]/seg[1]/#"}}],"#":{"value":"Helas ! je me défendrois mieux","id":"/div/quote/lg/l[6]/#"}},{"@rend":"i","seg":[{"@type":"tab","#":{"value":"    ","id":"/div/quote/lg/l[7]/seg[0]/#"}},{"@type":"tab","#":{"value":"    ","id":"/div/quote/lg/l[7]/seg[1]/#"}}],"#":{"value":"Contre les soupirs &amp; les larmes.","id":"/div/quote/lg/l[7]/#"}}]}},"ref":{"@target":"images/1680-02_283.JPG","figure":{"graphic":{"@url":"images/1680-02_283.JPG"}}}}}