{"div":{"@xmlns":"http://www.tei-c.org/ns/1.0","@type":"article","@xml:id":"MG-1702-08_211","head":{"value":"[Ode sur la guerre présente]","id":"/div/head"},"bibl":{"title":{"value":"Mercure galant","id":"/div/bibl/title"},"#":{"value":", août 1702 [tome 11], p. 211-216.","id":"/div/bibl/#"}},"p":{"value":"Vous trouverez les Vers qui suivent assez naturellement placez aprés cette défaite. Ils sont de Mr l’Abbé Charlet, qui nous a déja donné divers Odes latines, que d’habiles Traducteurs ont renduës en Vers François : cet Abbé en a fait une nouvelle sur la guerre que les Allemans, les Anglois, &amp; les Hollandois ont declarée à la France &amp; à l’Espagne. La Traduction en a esté faite par Mr l’Abbé Mauguin, &amp; je vous l’envoye.","id":"/div/p"},"quote":{"#":[{"label":{"#":{"value":"SUR LA GUERRE PRESENTE.","id":"/div/quote/#[0]/label/#"},"lb":{},"hi":{"@rend":"i","#":{"value":"ODE.","id":"/div/quote/#[0]/label/hi/#"}}}},{"lg":{"l":[{"hi":{"@rend":"i","#":{"value":"Où vous entraîne encore une ardeur insensée ?","id":"/div/quote/#[1]/lg/l[0]/hi/#"}}},{"hi":{"@rend":"i","#":{"value":"Quoy ! Germains vous osez irriter les François,","id":"/div/quote/#[1]/lg/l[1]/hi/#"}}},{"hi":{"@rend":"i","#":{"value":"De ces Peuples Vainqueurs de vous de tant de Rois","id":"/div/quote/#[1]/lg/l[2]/hi/#"}}},{"hi":{"@rend":"i","#":{"value":"La memoire chez vous seroit-elle effacée.","id":"/div/quote/#[1]/lg/l[3]/hi/#"}}}]}},{"ab":{"@type":"ornament","#":{"value":"***","id":"/div/quote/#[2]/ab/#"}}},{"lg":{"l":[{"hi":{"@rend":"i","#":{"value":"La ruse est inutile, &amp; la surprise est vaine","id":"/div/quote/#[3]/lg/l[0]/hi/#"}}},{"hi":{"@rend":"i","#":{"value":"Contre de fiers Guerriers que la gloire conduit,","id":"/div/quote/#[3]/lg/l[1]/hi/#"}}},{"hi":{"@rend":"i","#":{"value":"La nuit comme le jour la Victoire les suit,","id":"/div/quote/#[3]/lg/l[2]/hi/#"}}},{"hi":{"@rend":"i","#":{"value":"Fuis, sage Eugene, fuis, ou ta perte est certaine.","id":"/div/quote/#[3]/lg/l[3]/hi/#"}}}]}},{"ab":{"@type":"ornament","#":{"value":"***","id":"/div/quote/#[4]/ab/#"}}},{"lg":{"l":[{"hi":{"@rend":"i","#":{"value":"Quand sans cesse à ruser ton esprit s’abandonne","id":"/div/quote/#[5]/lg/l[0]/hi/#"}}},{"hi":{"@rend":"i","#":{"value":"Tu crains un Ennemi toûjours victorieux,","id":"/div/quote/#[5]/lg/l[1]/hi/#"}}},{"hi":{"@rend":"i","#":{"value":"Mais si de tels moyens te semblent glorieux","id":"/div/quote/#[5]/lg/l[2]/hi/#"}}},{"hi":{"@rend":"i","#":{"value":"Tu peux quand tu voudras retourner à Cremone.","id":"/div/quote/#[5]/lg/l[3]/hi/#"}}}]}},{"ab":{"@type":"ornament","#":{"value":"***","id":"/div/quote/#[6]/ab/#"}}},{"lg":{"l":[{"hi":{"@rend":"i","#":{"value":"Voy pour surcroist de trouble à ton ame allarmée","id":"/div/quote/#[7]/lg/l[0]/hi/#"}}},{"hi":[{"@rend":"sc","#":{"value":"Philippe","id":"/div/quote/#[7]/lg/l[1]/hi[0]/#"}},{"@rend":"i","#":{"value":"contre toy conduire les François.","id":"/div/quote/#[7]/lg/l[1]/hi[1]/#"}}]},{"hi":{"@rend":"i","#":{"value":"Ce Heros glorieux sort du sang de nos Rois","id":"/div/quote/#[7]/lg/l[2]/hi/#"}}},{"hi":{"@rend":"i","#":{"value":"Et luy seul en valeur égale son Armée.","id":"/div/quote/#[7]/lg/l[3]/hi/#"}}}]}},{"ab":{"@type":"ornament","#":{"value":"***","id":"/div/quote/#[8]/ab/#"}}},{"lg":{"l":[{"hi":{"@rend":"i","#":{"value":"Quoy les Villes, les Forts, tout cede sans deffense,","id":"/div/quote/#[9]/lg/l[0]/hi/#"}}},{"hi":{"@rend":"i","#":{"value":"Fuis, Eugene, ou te rens ; Mars qui t’en fait la loy","id":"/div/quote/#[9]/lg/l[1]/hi/#"}}},{"hi":{"@rend":"i","#":{"value":"Ne veut pas qu’elle ait rien qui soit honteux pour toy","id":"/div/quote/#[9]/lg/l[2]/hi/#"}}},{"hi":{"@rend":"i","#":{"value":"Puisque tout doit ceder aux forces de la France.","id":"/div/quote/#[9]/lg/l[3]/hi/#"}}}]}},{"ab":{"@type":"ornament","#":{"value":"***","id":"/div/quote/#[10]/ab/#"}}},{"lg":{"l":[{"hi":{"@rend":"i","#":{"value":"Sarmates, &amp; Danois, vous Bataves rebelles,","id":"/div/quote/#[11]/lg/l[0]/hi/#"}}},{"hi":{"@rend":"i","#":{"value":"Accourez au secours des Germains vos amis ;","id":"/div/quote/#[11]/lg/l[1]/hi/#"}}},{"hi":{"@rend":"i","#":{"value":"Plus contre les François vous serez d’ennemis,","id":"/div/quote/#[11]/lg/l[2]/hi/#"}}},{"hi":{"@rend":"i","#":{"value":"Plus ils moissonneront de Palmes immortelles.","id":"/div/quote/#[11]/lg/l[3]/hi/#"}}}]}},{"ab":{"@type":"ornament","#":{"value":"***","id":"/div/quote/#[12]/ab/#"}}},{"lg":{"l":[{"hi":{"@rend":"i","#":{"value":"Couvrez de vos Vaisseaux la mer &amp; le rivage,","id":"/div/quote/#[13]/lg/l[0]/hi/#"}}},{"hi":{"@rend":"i","#":{"value":"Fiers Bretons, à vos Rois***** Sujets,","id":"/div/quote/#[13]/lg/l[1]/hi/#"}}},{"hi":{"@rend":"i","#":{"value":"Mais n’attendez pour prix de vos vastes projets,","id":"/div/quote/#[13]/lg/l[2]/hi/#"}}},{"hi":{"@rend":"i","#":{"value":"Que toutes les horreurs d’un funeste naufrage.","id":"/div/quote/#[13]/lg/l[3]/hi/#"}}}]}},{"ab":{"@type":"ornament","#":{"value":"***","id":"/div/quote/#[14]/ab/#"}}},{"lg":{"l":[{"hi":{"@rend":"i","#":{"value":"D’une valeur, François, à vous seuls naturelle,","id":"/div/quote/#[15]/lg/l[0]/hi/#"}}},{"hi":{"@rend":"i","#":{"value":"Bravez comme autrefois ce guerrier appareil","id":"/div/quote/#[15]/lg/l[1]/hi/#"}}},{"hi":{"@rend":"i","#":{"value":"C’est un nuage épais qui s’oppose au Soleil","id":"/div/quote/#[15]/lg/l[2]/hi/#"}}},{"hi":{"@rend":"i","#":{"value":"Et qu’il dissipera d’une seule étincelle.","id":"/div/quote/#[15]/lg/l[3]/hi/#"}}}]}},{"ab":{"@type":"ornament","#":{"value":"***","id":"/div/quote/#[16]/ab/#"}}},{"lg":{"l":[{"hi":{"@rend":"i","#":{"value":"Ainsi, Brave François, arme-toy de la Foudre","id":"/div/quote/#[17]/lg/l[0]/hi/#"}}},{"hi":{"@rend":"i","#":{"value":"Chez tous ces Rois jaloux, Va, cours porter l’effroy,","id":"/div/quote/#[17]/lg/l[1]/hi/#"}}},{"hi":{"@rend":"i","#":{"value":"Que ces fiers ennemis se rangent sous ta loy","id":"/div/quote/#[17]/lg/l[2]/hi/#"}}},{"hi":{"@rend":"i","#":{"value":"Ou qu’ils soient de nouveau par toy réduits en poudre.","id":"/div/quote/#[17]/lg/l[3]/hi/#"}}}]}},{"ab":{"@type":"ornament","#":{"value":"***","id":"/div/quote/#[18]/ab/#"}}},{"lg":{"l":[{"hi":{"@rend":"i","#":{"value":"C’est un Arrest rendu par le Dieu de la guerre","id":"/div/quote/#[19]/lg/l[0]/hi/#"}}},{"hi":{"@rend":"i","#":{"value":"En faveur du plus sage &amp; du plus grand des Rois ;","id":"/div/quote/#[19]/lg/l[1]/hi/#"}}},{"hi":{"@rend":"i","#":{"value":"Que l’Univers, dit-il, soit soumis à ses loix ;","id":"/div/quote/#[19]/lg/l[2]/hi/#"}}},{"hi":{"@rend":"i","#":{"value":"C’est à luy de calmer ou de troubler la terre.","id":"/div/quote/#[19]/lg/l[3]/hi/#"}}}]}}]}}}