{"div":{"@":{"xmlns":"http://www.tei-c.org/ns/1.0","type":"article","xml:id":"MG-1700-12_134","resp":"wordpro"},"#":[{"head":{"value":"[Autres Madrigaux au Roy, &amp; au Roy d’Espagne]","id":"/div/#[0]/head"}},{"bibl":{"title":{"value":"Mercure galant","id":"/div/#[1]/bibl/title"},"#":{"value":", décembre 1700 [tome 12], p. 134-140.","id":"/div/#[1]/bibl/#"}}},{"p":{"value":"Voicy encore quelques autres Vers sur ce que Monseigneur le Duc d’Anjou a esté appellé à la Couronne d’Espagne. Les premiers sont de l’illustre Mademoiselle de Scudery.","id":"/div/#[2]/p"}},{"quote":{"lg":{"l":[{"@rend":"i","#":{"value":"J’Ay prédit mille fois que mon divin Heros","id":"/div/#[3]/quote/lg/l[0]/#"}},{"@rend":"i","#":{"value":" Dans le plus paisible repos","id":"/div/#[3]/quote/lg/l[1]/#"}},{"@rend":"i","#":{"value":"Regneroit par son Sang sur la terre &amp; sur l’onde,","id":"/div/#[3]/quote/lg/l[2]/#"}},{"@rend":"i","#":{"value":"Et qu’il seroit toujours le plus grand Roy du monde ;","id":"/div/#[3]/quote/lg/l[3]/#"}},{"@rend":"i","#":{"value":"Mais ce qui me ravit en cet heureux moment,","id":"/div/#[3]/quote/lg/l[4]/#"}},{"@rend":"i","#":{"value":"Nous voyons aujourd’huy ce grand évenement.","id":"/div/#[3]/quote/lg/l[5]/#"}}]}}},{"p":{"value":"Mademoiselle d’Alerac de la Charce, aussi considerable par son esprit que par sa naissance, a fait les deux Madrigaux qui suivent.","id":"/div/#[4]/p"}},{"quote":[{"label":{"value":"AU ROY.","id":"/div/#[5]/quote[0]/label"},"lg":{"l":[{"@rend":"i","#":{"value":"Heros, plus grand cent fois que ne fut Alexandre,","id":"/div/#[5]/quote[0]/lg/l[0]/#"}},{"@rend":"i","#":{"value":"En rendant comme luy ce que vous avez pris,","id":"/div/#[5]/quote[0]/lg/l[1]/#"}},{"@rend":"i","#":{"value":"Les cœurs vous sont restez ils vous sont tous soumis,","id":"/div/#[5]/quote[0]/lg/l[2]/#"}},{"@rend":"i","#":{"value":" L’Espagne vient de nous l’apprendre.","id":"/div/#[5]/quote[0]/lg/l[3]/#"}},{"@rend":"i","#":{"value":"Pour Maistre elle voudroit nostre Auguste LOUIS ;","id":"/div/#[5]/quote[0]/lg/l[4]/#"}},{"@rend":"i","#":{"value":"A ce noble bonheur ne pouvant pas prétendre,","id":"/div/#[5]/quote[0]/lg/l[5]/#"}},{"@rend":"i","#":{"value":" Elle luy demande son Fils.","id":"/div/#[5]/quote[0]/lg/l[6]/#"}}]}},{"label":{"#1":{"value":"POUR LE ROY","id":"/div/#[5]/quote[1]/label/#1"},"lb":{},"#2":{"value":"d’Espagne.","id":"/div/#[5]/quote[1]/label/#2"}},"lg":{"l":[{"@rend":"i","#":{"value":" De l’Astre qu’annonce l’Aurore","id":"/div/#[5]/quote[1]/lg/l[0]/#"}},{"@rend":"i","#":{"value":"L’Espagne sur ses champs voit toujours l’appareil.","id":"/div/#[5]/quote[1]/lg/l[1]/#"}},{"@rend":"i","#":{"value":"Quand on croit chez Thetis qu’il se livre au sommeil,","id":"/div/#[5]/quote[1]/lg/l[2]/#"}},{"@rend":"i","#":{"value":"Dans la nouvelle Espagne on voit qu’il brille encore,","id":"/div/#[5]/quote[1]/lg/l[3]/#"}},{"@rend":"i","#":{"value":" Et cette fiere Nation","id":"/div/#[5]/quote[1]/lg/l[4]/#"}},{"@rend":"i","#":{"value":" Suivant la noble ambition","id":"/div/#[5]/quote[1]/lg/l[5]/#"}},{"@rend":"i","#":{"value":" Qui la guide &amp; qui la devore,","id":"/div/#[5]/quote[1]/lg/l[6]/#"}},{"@rend":"i","#":{"value":"Demande encor son digne Fils pour Roy,","id":"/div/#[5]/quote[1]/lg/l[7]/#"}},{"@rend":"i","#":{"value":" Heureux qui vivra sous sa loy !","id":"/div/#[5]/quote[1]/lg/l[8]/#"}},{"@rend":"i","#":{"value":" Dés sa naissance l’on l’adore !","id":"/div/#[5]/quote[1]/lg/l[9]/#"}},{"@rend":"i","#":{"value":"Ah, que de tristes pleurs, &amp; que de tendres cris","id":"/div/#[5]/quote[1]/lg/l[10]/#"}},{"@rend":"i","#":{"value":" Nous coûtera cette cruelle absence !","id":"/div/#[5]/quote[1]/lg/l[11]/#"}},{"@rend":"i","#":{"value":"Il nous reste, il est vray trois grands Princes en France ;","id":"/div/#[5]/quote[1]/lg/l[12]/#"}},{"@rend":"i","#":{"value":"Mais peut on trop avoir du beau Sang de LOUIS ?","id":"/div/#[5]/quote[1]/lg/l[13]/#"}}]}}]},{"p":{"value":"Mademoiselle Bernard est entrée dans le noble empressement de ceux qui se sont hâtez d’écrire sur le grand évenement qui fait parler aujourd’huy toute l’Europe. Voicy ce que luy a inspiré son heureux genie.","id":"/div/#[6]/p"}},{"quote":{"lg":{"l":[{"@rend":"i","#":{"value":" Que vois-je ? Quel éclat soudain !","id":"/div/#[7]/quote/lg/l[0]/#"}},{"@rend":"i","#":{"value":"Quelle Divinité brille aux yeux de la France !","id":"/div/#[7]/quote/lg/l[1]/#"}},{"@rend":"i","#":{"value":" C’est la Fortune qui s’avance","id":"/div/#[7]/quote/lg/l[2]/#"}},{"@rend":"i","#":{"value":" Avec vingt sceptres à la main.","id":"/div/#[7]/quote/lg/l[3]/#"}},{"@rend":"i","#":{"value":"A ce pompeux aspect loin que Loüis s’empresse","id":"/div/#[7]/quote/lg/l[4]/#"}},{"@rend":"i","#":{"value":" D’accepter ces dons précieux,","id":"/div/#[7]/quote/lg/l[5]/#"}},{"@rend":"i","#":{"value":"Il songe à consulter l’équitable Déesse","id":"/div/#[7]/quote/lg/l[6]/#"}},{"@rend":"i","#":{"value":"  Qui porte un bandeau sur les yeux.","id":"/div/#[7]/quote/lg/l[7]/#"}},{"@rend":"i","#":{"value":"  A ses Conseils elle preside,","id":"/div/#[7]/quote/lg/l[8]/#"}},{"@rend":"i","#":{"value":"  La Fortune en attend la loy ;","id":"/div/#[7]/quote/lg/l[9]/#"}},{"@rend":"i","#":{"value":" C’est la Justice qui decide","id":"/div/#[7]/quote/lg/l[10]/#"}},{"@rend":"i","#":{"value":"  Et sa voix seule fait un Roy.","id":"/div/#[7]/quote/lg/l[11]/#"}},{"@rend":"i","#":{"value":"Peuples qui remplissez l’un &amp; l’autre Hemisphere","id":"/div/#[7]/quote/lg/l[12]/#"}},{"@rend":"i","#":{"value":"Joüissez du bonheur qui vous est presenté,","id":"/div/#[7]/quote/lg/l[13]/#"}},{"@rend":"i","#":{"value":"Philippe a de Loüis le noble caractére.","id":"/div/#[7]/quote/lg/l[14]/#"}},{"@rend":"i","#":{"value":"Si vous connoissez bien vostre félicité,","id":"/div/#[7]/quote/lg/l[15]/#"}},{"@rend":"i","#":{"value":"Vous n’aurez plus de vœux à faire.","id":"/div/#[7]/quote/lg/l[16]/#"}}]}}}]}}