{"div":{"@xmlns":"http://www.tei-c.org/ns/1.0","@type":"article","@xml:id":"MG-1697-12_283","@resp":"mercure","head":{"value":"[Avis]*","id":"/div/head"},"bibl":{"title":{"value":"Mercure galant","id":"/div/bibl/title"},"#":{"value":", décembre 1697 [tome 12], p. 283.","id":"/div/bibl/#"}},"p":{"#1":{"value":"Les Comediens du Roy representent depuis trois semaines une Piece nouvelle, intitulée ","id":"/div/p/#1"},"hi":{"@rend":"i","#":{"value":"Pilade &amp; Oreste","id":"/div/p/hi/#"}},"#2":{"value":", qui fait grand honneur à son Auteur. Les situations en sont tres-heureuses, &amp; excitent des sentimens de pitié qui rendent cette Piece tres-agreable. Je suis, Madame, vostre, &amp;c.","id":"/div/p/#2"}}}}