{"div":{"@xmlns":"http://www.tei-c.org/ns/1.0","@type":"article","@xml:id":"MG-1686-06_178","@resp":"angele","head":{"value":"Air nouveau","id":"/div/head"},"bibl":{"title":{"value":"Mercure galant","id":"/div/bibl/title"},"#":{"value":", juin 1686 [tome 7], p. 178-179.","id":"/div/bibl/#"}},"p":{"value":"Vous devez estre contente de l'Air nouveau que je vous envoye, puis qu'une personne des plus difficiles en Musique, &amp; qui chante avec le plus de justesse, l'a appellé son Air favory.","id":"/div/p"},"quote":{"label":{"value":"AIR NOUVEAU.","id":"/div/quote/label"},"note":{"@":{"resp":"author","place":"margin"},"#":[{"hi":{"@rend":"i","#":{"value":"Avis pour placer les Figures","id":"/div/quote/note/#[0]/hi/#"}}},{"#":{"value":" : l’Air qui commence par ","id":"/div/quote/note/#[1]/#"}},{"hi":{"@rend":"i","#":{"value":"Le Printemps commence à paroistre","id":"/div/quote/note/#[2]/hi/#"}}},{"#":{"value":", doit regarder la page 179.","id":"/div/quote/note/#[3]/#"}}]},"lg":{"l":[{"@rend":"i","#":{"value":"Le Printemps commence à paroistre,","id":"/div/quote/lg/l[0]/#"}},{"@rend":"i","#":{"value":"Il s'est enfin rendu le maistre","id":"/div/quote/lg/l[1]/#"}},{"@rend":"i","#":{"value":"De l'Hyver contre luy si long-temps révolté.","id":"/div/quote/lg/l[2]/#"}},{"@rend":"i","#":{"value":"Amour, amour fais-en de mesme ;","id":"/div/quote/lg/l[3]/#"}},{"@rend":"i","#":{"value":"Contre le cœur d'une ingrate beauté","id":"/div/quote/lg/l[4]/#"}},{"@rend":"i","#":{"value":"Toûjours plein de severité,","id":"/div/quote/lg/l[5]/#"}},{"@rend":"i","#":{"value":"Fais sentir ton pouvoir extrême.","id":"/div/quote/lg/l[6]/#"}}]}},"ref":{"@target":"images/1686-06_178.JPG","figure":{"graphic":{"@url":"images/1686-06_178.JPG"}}}}}