{"div":{"@xmlns":"http://www.tei-c.org/ns/1.0","@type":"article","@xml:id":"MG-1685-12e_089","@resp":"wordpro","head":{"value":"Si l’on peut mourir d’amour","id":"/div/head"},"bibl":{"title":{"value":"Extraordinaire du Mercure galant","id":"/div/bibl/title"},"#":{"value":", quartier d’octobre 1685 (tome XXXII), p. 89-90","id":"/div/bibl/#"}},"quote":{"label":{"value":"Si l’on peut mourir d’amour.","id":"/div/quote/label"},"lg":{"l":[{"@rend":"i","#":{"value":" Aimer &amp; n’estre pas aimé","id":"/div/quote/lg/l[0]/#"}},{"@rend":"i","#":{"value":" De l’objet qui nous tient charmé,","id":"/div/quote/lg/l[1]/#"}},{"@rend":"i","#":{"value":" Jadis nous mettoit à la gehenne.","id":"/div/quote/lg/l[2]/#"}},{"@rend":"i","#":{"value":" L’un &amp; l’autre Sexe aujourd’huy","id":"/div/quote/lg/l[3]/#"}},{"@rend":"i","#":{"value":"Sur le moindre sujet rompt la plus belle chaine","id":"/div/quote/lg/l[4]/#"}},{"@rend":"i","#":{"value":" Sans en sentir le moindre ennuy.","id":"/div/quote/lg/l[5]/#"}},{"@rend":"i","#":{"value":" Non, certes, ce n’est plus la mode","id":"/div/quote/lg/l[6]/#"}},{"@rend":"i","#":{"value":"D’aller chez les defunts pour avoir trop d’amour,","id":"/div/quote/lg/l[7]/#"}},{"@rend":"i","#":{"value":" Et la maxime est incommode","id":"/div/quote/lg/l[8]/#"}},{"@rend":"i","#":{"value":" D’aimer à present plus d’un jour.","id":"/div/quote/lg/l[9]/#"}},{"@rend":"i","#":{"value":"Que deux Amans, d’une pudique flame","id":"/div/quote/lg/l[10]/#"}},{"@rend":"i","#":{"value":" S’aiment, sans partager leur ame ;","id":"/div/quote/lg/l[11]/#"}},{"@rend":"i","#":{"value":" Cela pourra se rencontrer,","id":"/div/quote/lg/l[12]/#"}},{"@rend":"i","#":{"value":"Mais difficilement pourroit-on le montrer.","id":"/div/quote/lg/l[13]/#"}},{"@rend":"i","#":{"value":" Que cela soit ! ils goûtent avec joye","id":"/div/quote/lg/l[14]/#"}},{"@rend":"i","#":{"value":" Tous les plaisirs que l’amour peut souffrir,","id":"/div/quote/lg/l[15]/#"}},{"@rend":"i","#":{"value":" Mais il ne faut pas que l’on croye","id":"/div/quote/lg/l[16]/#"}},{"@rend":"i","#":{"value":" Qu’ils en puissent mourir.","id":"/div/quote/lg/l[17]/#"}},{"@rend":"i","#":{"value":"Que l’on n’appelle point cecy Rodomontade :","id":"/div/quote/lg/l[18]/#"}},{"@rend":"i","#":{"value":" Philis, dont je fais tant de cas,","id":"/div/quote/lg/l[19]/#"}},{"@rend":"i","#":{"value":"S’éloigne, &amp; je me vois privé de ses appas.","id":"/div/quote/lg/l[20]/#"}},{"@rend":"i","#":{"value":" Je l’aime, j’en seray malade,","id":"/div/quote/lg/l[21]/#"}},{"@rend":"i","#":{"value":" Mais je n’en mouray pas.","id":"/div/quote/lg/l[22]/#"}}]},"p":{"value":"Le mesme.","id":"/div/quote/p"}}}}